{
  "documents": [
    {
      "id": "RETURN-001",
      "type": "return",
      "status": "in_progress",
      "totalLines": 2,
      "responsible": "Иванов И.И.",
      "createdAt": 1698912000000,
      "updatedAt": 1698915600000
    }
  ],
  "lines": [
    {
      "id": "RETURN-001-L1",
      "documentId": "RETURN-001",
      "productId": "P002",
      "productName": "Чай Ahmad Earl Grey 100г",
      "productSku": "AHM-100-EG",
      "barcode": "5054881234567",
      "quantity": 2,
      "quantityPlan": 2,
      "quantityFact": 2,
      "status": "completed",
      "reason": "damaged",
      "addedAt": 1698912600000
    },
    {
      "id": "RETURN-001-L2",
      "documentId": "RETURN-001",
      "productId": "P004",
      "productName": "Молоко 3.2% 1л",
      "productSku": "MLK-32-1L",
      "barcode": "4607012345678",
      "quantity": 5,
      "quantityPlan": 5,
      "quantityFact": 5,
      "status": "completed",
      "reason": "expired",
      "addedAt": 1698913200000
    }
  ]
}
